ahmethingra/__init__.py
ahmethingra-0.1.0.dist-info/METADATA
ahmethingra-0.1.0.dist-info/WHEEL
ahmethingra-0.1.0.dist-info/top_level.txt
ahmethingra-0.1.0.dist-info/RECORD
