Metadata-Version: 2.2
Name: ahmethingra
Version: 0.1.0
Summary: وصف مكتبتك
Home-page: https://pypi.org/project/ahmethingra/
Author: Ahmed Asaad
Author-email: ahmadasaadmajed1@gmail.com
Classifier: Programming Language :: Python :: 3
Classifier: License :: OSI Approved :: MIT License
Classifier: Operating System :: OS Independent
Requires-Python: >=3.6
Dynamic: author
Dynamic: author-email
Dynamic: classifier
Dynamic: home-page
Dynamic: requires-python
Dynamic: summary
